{
  "date": "2015-03-06",
  "platform": "OVA",
  "images": {
    "small": "https://lain.bgm.tv/r/200/pic/cover/l/58/0a/126180_coShd.jpg",
    "grid": "https://lain.bgm.tv/r/100/pic/cover/l/58/0a/126180_coShd.jpg",
    "large": "https://lain.bgm.tv/pic/cover/l/58/0a/126180_coShd.jpg",
    "medium": "https://lain.bgm.tv/r/800/pic/cover/l/58/0a/126180_coShd.jpg",
    "common": "https://lain.bgm.tv/r/400/pic/cover/l/58/0a/126180_coShd.jpg"
  },
  "summary": "妹の万引きが原因で脅され、男どもから嬲り者にされる新任教師の玲奈。\r\nいやらしいオトナのマ●コにローターを入れたままの出勤強制! \r\n\r\nお仕事中にも3回絶頂! \r\n校舎の中で姉妹サンドされ、ぶっかけナカ出し絶頂地獄! \r\n\r\n他人にはイエナイ淫らな秘め事。\r\n美人姉妹のヘンタイ姉妹どんぶり、完成。",
  "name": "イエナイコト THE ANIMATION",
  "name_cn": "不能说的事情",
  "tags": [
    {
      "name": "里番",
      "count": 168,
      "total_cont": 0
    },
    {
      "name": "BOOTLEG",
      "count": 52,
      "total_cont": 0
    },
    {
      "name": "胁迫",
      "count": 41,
      "total_cont": 0
    },
    {
      "name": "教师",
      "count": 36,
      "total_cont": 0
    },
    {
      "name": "巨乳",
      "count": 35,
      "total_cont": 0
    },
    {
      "name": "2015",
      "count": 30,
      "total_cont": 0
    },
    {
      "name": "调教",
      "count": 25,
      "total_cont": 0
    },
    {
      "name": "NTR",
      "count": 20,
      "total_cont": 0
    },
    {
      "name": "OVA",
      "count": 18,
      "total_cont": 0
    },
    {
      "name": "無修正",
      "count": 14,
      "total_cont": 0
    },
    {
      "name": "无码",
      "count": 13,
      "total_cont": 0
    },
    {
      "name": "2015年3月",
      "count": 8,
      "total_cont": 0
    },
    {
      "name": "18禁",
      "count": 7,
      "total_cont": 0
    },
    {
      "name": "里",
      "count": 6,
      "total_cont": 0
    },
    {
      "name": "黑丝",
      "count": 5,
      "total_cont": 0
    },
    {
      "name": "音乐加分",
      "count": 4,
      "total_cont": 0
    },
    {
      "name": "2015年",
      "count": 4,
      "total_cont": 0
    },
    {
      "name": "18X",
      "count": 4,
      "total_cont": 0
    },
    {
      "name": "已下载",
      "count": 3,
      "total_cont": 0
    },
    {
      "name": "已下",
      "count": 3,
      "total_cont": 0
    },
    {
      "name": "里番2015",
      "count": 3,
      "total_cont": 0
    },
    {
      "name": "原创",
      "count": 3,
      "total_cont": 0
    },
    {
      "name": "其他",
      "count": 2,
      "total_cont": 0
    },
    {
      "name": "实用",
      "count": 2,
      "total_cont": 0
    },
    {
      "name": "步兵裡番",
      "count": 2,
      "total_cont": 0
    },
    {
      "name": "雁が首",
      "count": 2,
      "total_cont": 0
    },
    {
      "name": "漫画",
      "count": 2,
      "total_cont": 0
    },
    {
      "name": "2015里番",
      "count": 2,
      "total_cont": 0
    },
    {
      "name": "漫改",
      "count": 2,
      "total_cont": 0
    },
    {
      "name": "凌辱",
      "count": 2,
      "total_cont": 0
    }
  ],
  "infobox": [
    {
      "key": "中文名",
      "value": "不能说的事情"
    },
    {
      "key": "话数",
      "value": "1"
    },
    {
      "key": "发售日",
      "value": "2015年3月6日"
    },
    {
      "key": "官方网站",
      "value": "http://www.ms-pictures.com/"
    },
    {
      "key": "导演",
      "value": "大山尊"
    },
    {
      "key": "人物设定",
      "value": "稜線漫步"
    },
    {
      "key": "原画",
      "value": "うねり"
    },
    {
      "key": "第二原画",
      "value": "マルタポーク、司"
    },
    {
      "key": "色彩设计",
      "value": "天空の月"
    },
    {
      "key": "补间动画",
      "value": "スタジオシュテム"
    },
    {
      "key": "上色",
      "value": "スタジオシュテム"
    },
    {
      "key": "色彩指定",
      "value": "天空の月"
    },
    {
      "key": "色彩检查",
      "value": "天空の月"
    },
    {
      "key": "美术",
      "value": "飯田和昭、仲嶋栄人"
    },
    {
      "key": "摄影",
      "value": "Tight-Rope"
    },
    {
      "key": "剪辑",
      "value": "新海コウキ；剪辑助理：隣のB-Boy"
    },
    {
      "key": "剪辑室",
      "value": "柳編集室"
    },
    {
      "key": "音乐",
      "value": "gion-shoj/Rock'n' Banana"
    },
    {
      "key": "音响监督",
      "value": "吉川駿河"
    },
    {
      "key": "制作管理:",
      "value": "いそこ"
    },
    {
      "key": "音响",
      "value": "有限会社ロックンバナナ"
    },
    {
      "key": "主题歌演出",
      "value": "莓依"
    },
    {
      "key": "主题歌作词",
      "value": "IKUTO"
    },
    {
      "key": "主题歌作曲",
      "value": "IKUTO"
    },
    {
      "key": "主题歌编曲",
      "value": "IKUTO"
    },
    {
      "key": "制作制片人",
      "value": "上村直巳"
    },
    {
      "key": "制作进行",
      "value": "Kevlar"
    },
    {
      "key": "制作",
      "value": "ピークハント"
    },
    {
      "key": "价格",
      "value": "￥3,800 (税込￥4,104)"
    }
  ],
  "rating": {
    "rank": 8633,
    "total": 190,
    "count": {
      "1": 7,
      "2": 11,
      "3": 18,
      "4": 31,
      "5": 58,
      "6": 47,
      "7": 5,
      "8": 6,
      "9": 4,
      "10": 3
    },
    "score": 4.9
  },
  "total_episodes": 1,
  "collection": {
    "on_hold": 37,
    "dropped": 38,
    "wish": 152,
    "collect": 409,
    "doing": 14
  },
  "id": 126180,
  "eps": 1,
  "meta_tags": [
    "OVA"
  ],
  "volumes": 0,
  "series": false,
  "locked": false,
  "nsfw": true,
  "type": 2
}