{
  "date": "2014-01-30",
  "platform": "OVA",
  "images": {
    "small": "https://lain.bgm.tv/r/200/pic/cover/l/e3/b3/95609_C6MyU.jpg",
    "grid": "https://lain.bgm.tv/r/100/pic/cover/l/e3/b3/95609_C6MyU.jpg",
    "large": "https://lain.bgm.tv/pic/cover/l/e3/b3/95609_C6MyU.jpg",
    "medium": "https://lain.bgm.tv/r/800/pic/cover/l/e3/b3/95609_C6MyU.jpg",
    "common": "https://lain.bgm.tv/r/400/pic/cover/l/e3/b3/95609_C6MyU.jpg"
  },
  "summary": "雄太は同じ学校に通う2人の姉、千代・千夏と3人で暮らしている。\r\nある日、ゆうたが千代の代わりに洗濯物を畳んでいると、きわどいパンツを見つけてびっくり。\r\nまさか夏姉の物とは思えない、だとしたら千代姉の……!?\r\nあんな清楚な千代姉がこんな大胆な下着を身に付けているなんて！\r\nパンツを手にしたまま固まるゆうた。しかし、それは千夏の物だったのだ。",
  "name": "Swing Out Sisters 完全版",
  "name_cn": "摇摆姐妹 完全版",
  "tags": [
    {
      "name": "里番",
      "count": 717,
      "total_cont": 0
    },
    {
      "name": "姐控",
      "count": 264,
      "total_cont": 0
    },
    {
      "name": "OVA",
      "count": 184,
      "total_cont": 0
    },
    {
      "name": "姐妹丼",
      "count": 163,
      "total_cont": 0
    },
    {
      "name": "2014",
      "count": 157,
      "total_cont": 0
    },
    {
      "name": "18禁",
      "count": 89,
      "total_cont": 0
    },
    {
      "name": "实用",
      "count": 87,
      "total_cont": 0
    },
    {
      "name": "近亲相奸",
      "count": 78,
      "total_cont": 0
    },
    {
      "name": "纯爱",
      "count": 77,
      "total_cont": 0
    },
    {
      "name": "漫画改",
      "count": 63,
      "total_cont": 0
    },
    {
      "name": "撸出血",
      "count": 55,
      "total_cont": 0
    },
    {
      "name": "18X",
      "count": 34,
      "total_cont": 0
    },
    {
      "name": "巨乳",
      "count": 32,
      "total_cont": 0
    },
    {
      "name": "双嫁去死",
      "count": 21,
      "total_cont": 0
    },
    {
      "name": "后宫",
      "count": 18,
      "total_cont": 0
    },
    {
      "name": "わたせとしひろ",
      "count": 18,
      "total_cont": 0
    },
    {
      "name": "R18",
      "count": 16,
      "total_cont": 0
    },
    {
      "name": "BREAKBOTTLE",
      "count": 12,
      "total_cont": 0
    },
    {
      "name": "2014年",
      "count": 11,
      "total_cont": 0
    },
    {
      "name": "漫改",
      "count": 9,
      "total_cont": 0
    },
    {
      "name": "マンガ原作",
      "count": 9,
      "total_cont": 0
    },
    {
      "name": "姐弟",
      "count": 8,
      "total_cont": 0
    },
    {
      "name": "婚纱",
      "count": 8,
      "total_cont": 0
    },
    {
      "name": "里",
      "count": 8,
      "total_cont": 0
    },
    {
      "name": "JK",
      "count": 7,
      "total_cont": 0
    },
    {
      "name": "incest",
      "count": 7,
      "total_cont": 0
    },
    {
      "name": "姐妹",
      "count": 6,
      "total_cont": 0
    },
    {
      "name": "姐系",
      "count": 5,
      "total_cont": 0
    },
    {
      "name": "2014年1月",
      "count": 5,
      "total_cont": 0
    },
    {
      "name": "黑丝",
      "count": 4,
      "total_cont": 0
    }
  ],
  "infobox": [
    {
      "key": "中文名",
      "value": "摇摆姐妹 完全版"
    },
    {
      "key": "话数",
      "value": "1"
    },
    {
      "key": "发售日",
      "value": "2014年1月30日"
    },
    {
      "key": "官方网站",
      "value": "http://sos-ova.com/top.html"
    },
    {
      "key": "作画监督",
      "value": "明雄、光鹿、梅酒"
    },
    {
      "key": "人物设定",
      "value": "明雄"
    },
    {
      "key": "原画",
      "value": "長崎五郎、Jcube、しそ"
    },
    {
      "key": "色彩指定",
      "value": "はなのら"
    },
    {
      "key": "背景美术",
      "value": "芝久保真峻、絵師里美、伊井田和昭、芝久保りえ"
    },
    {
      "key": "剪辑",
      "value": "深大ラボ"
    },
    {
      "key": "音响监督",
      "value": "やまとひと"
    },
    {
      "key": "音乐",
      "value": "LIT-HUM"
    },
    {
      "key": "音响",
      "value": "Strawberry Lab"
    },
    {
      "key": "制片人",
      "value": "狩野修"
    }
  ],
  "rating": {
    "rank": 1923,
    "total": 834,
    "count": {
      "1": 4,
      "2": 2,
      "3": 8,
      "4": 9,
      "5": 59,
      "6": 145,
      "7": 287,
      "8": 211,
      "9": 52,
      "10": 57
    },
    "score": 7.2
  },
  "total_episodes": 1,
  "collection": {
    "on_hold": 104,
    "dropped": 73,
    "wish": 863,
    "collect": 1446,
    "doing": 56
  },
  "id": 95609,
  "eps": 1,
  "meta_tags": [
    "R18",
    "OVA",
    "漫画改"
  ],
  "volumes": 0,
  "series": false,
  "locked": false,
  "nsfw": true,
  "type": 2
}